Project 1.2/alu.v
module alu(input [3:0]FS,
input [2:0]SH,
input [7:0]A,
input [7:0]B,
input [7:0]IN,
input [7:0]INK,

output reg [7:0]F,
output reg N, //negative
output reg Zero, //zero
output reg C, //carry
output reg V, //V
output reg D);

 //data_branch
reg [7:0]overflowregister;
// function select
always @(*) begin
  case (FS)
    4'b0000: F = 8'b0; // No Operation
    4'b0001: F = A + B; //ADD
    4'b0010: F = B; // Output 2
    4'b0011: F = (A<B)?8'b1:8'b0; // Set if Less Than
    4'b0100: F = A & B; // AND
    4'b0101: F = A; // Load
    4'b0110: F = A - B; // Subtract Immediate Unsigned
    4'b0111: F = A << SH; // Logical Shift Left;
    4'b1000: F = B; // Input
    4'b1001: F = A ^ B; // Exclusive-OR Immediate
    4'b1010: F = A + B; // Add Immediate
   // 4'b1011: F = //branch zero
   // 4'b1100: F = //branch non zero
    4'b1101: F = A;//store
  //  4'b1110: F = (FS == 4'b0001) ? A : B;//Move
  //  4'b1111: F = //Jump
    default: F = 8'b0;
  endcase

  if(F == 4'b0) Zero=1'b1;
    else Zero=1'b0; //set Z flagif F is 0
	if(F[7] == 1'b1) N=1'b1;
	  else N=1'b0; //set N status terminal based on MSB
	if(F[7] == 1'b1) C=1'b1; 
	  else C=1'b0; //set C if add/sub gives carry
  if (FS == 4'b0001) V = ( (A[7] == B[7]) && (A[7] !=  F[7]));
  if (FS == 4'b1010) V = ( (A[7] == B[7]) && (A[7] !=  F[7])) ? 1'b1 : 1'b0;
    else if(FS == 4'b0110) begin
    overflowregister = ~B+8'b1;
    V = ( (A[7] == overflowregister[7]) && (A[7] !=  F[7])) ? 1'b1 : 1'b0;
    end
end

endmodule

Project 1.2/alu_tb.v
`timescale 1ns/1ps
`include "alu.v"

module alu_tb();
reg [3:0]FS;
reg [2:0]SH;
reg [7:0]A;
reg [7:0]B;
reg [7:0]IN;
reg [7:0]INK;

wire [7:0]F;
wire N; //negative
wire Zero; //zero
wire C; //carry
wire V; //overflow
wire D;
integer i;

alu uut(
    .FS(FS), .SH(SH), .A(A), .B(B), .IN(IN), .INK(INK), 
    .F(F), .N(N), .Zero(Zero), .C(C), .V(V), .D(D)
    );
    initial begin
        A= 8'b1111;
        B= 8'b1110;
        FS = 4'h0;
        SH = 8'b0001;

        $dumpfile("alu_tb.vcd");
        $dumpvars(0, alu_tb);
        $display("Test");

        for (i=0;i<=15;i=i+1) begin
        FS = FS+8'b0001;
        #10;
        end

        A = 8'hF6;
        B = 8'h0A;
    end
endmodule

Project 1.2/alu_tb.vcd
$date
	Tue Feb 14 04:58:09 2023
$end
$version
	Icarus Verilog
$end
$timescale
	1ps
$end
$scope module alu_tb $end
$var wire 1 ! Zero $end
$var wire 1 " V $end
$var wire 1 # N $end
$var wire 8 $ F [7:0] $end
$var wire 1 % D $end
$var wire 1 & C $end
$var reg 8 ' A [7:0] $end
$var reg 8 ( B [7:0] $end
$var reg 4 ) FS [3:0] $end
$var reg 8 * IN [7:0] $end
$var reg 8 + INK [7:0] $end
$var reg 3 , SH [2:0] $end
$var integer 32 - i [31:0] $end
$scope module uut $end
$var wire 8 . A [7:0] $end
$var wire 8 / B [7:0] $end
$var wire 4 0 FS [3:0] $end
$var wire 8 1 IN [7:0] $end
$var wire 8 2 INK [7:0] $end
$var wire 3 3 SH [2:0] $end
$var reg 1 & C $end
$var reg 1 % D $end
$var reg 8 4 F [7:0] $end
$var reg 1 # N $end
$var reg 1 " V $end
$var reg 1 ! Zero $end
$var reg 8 5 overflowregister [7:0] $end
$upscope $end
$upscope $end
$enddefinitions $end
$comment Show the parameter values. $end
$dumpall
$end
#0
$dumpvars
bx 5
b11101 4
b1 3
bx 2
bx 1
b1 0
b1110 /
b1111 .
b0 -
b1 ,
bx +
bx *
b1 )
b1110 (
b1111 '
0&
x%
b11101 $
0#
0"
0!
$end
#10000
b1110 $
b1110 4
b10 )
b10 0
b1 -
#20000
1!
b0 $
b0 4
b11 )
b11 0
b10 -
#30000
0!
b1110 $
b1110 4
b100 )
b100 0
b11 -
#40000
b1111 $
b1111 4
b101 )
b101 0
b100 -
#50000
b11110010 5
b1 $
b1 4
b110 )
b110 0
b101 -
#60000
b11110 $
b11110 4
b111 )
b111 0
b110 -
#70000
b1110 $
b1110 4
b1000 )
b1000 0
b111 -
#80000
b1 $
b1 4
b1001 )
b1001 0
b1000 -
#90000
b11101 $
b11101 4
b1010 )
b1010 0
b1001 -
#100000
1!
b0 $
b0 4
b1011 )
b1011 0
b1010 -
#110000
b1100 )
b1100 0
b1011 -
#120000
0!
b1111 $
b1111 4
b1101 )
b1101 0
b1100 -
#130000
1!
b0 $
b0 4
b1110 )
b1110 0
b1101 -
#140000
b1111 )
b1111 0
b1110 -
#150000
b0 )
b0 0
b1111 -
#160000
b1010 (
b1010 /
b11110110 '
b11110110 .
b10000 -
